LICENSE
MANIFEST.in
README.rst
setup.py
txproductpages/__init__.py
txproductpages/connection.py
txproductpages/exceptions.py
txproductpages/milestones.py
txproductpages/release.py
txproductpages.egg-info/PKG-INFO
txproductpages.egg-info/SOURCES.txt
txproductpages.egg-info/dependency_links.txt
txproductpages.egg-info/not-zip-safe
txproductpages.egg-info/requires.txt
txproductpages.egg-info/top_level.txt