Metadata-Version: 1.1
Name: txproductpages
Version: 1.2.0
Summary: Twisted API for Red Hat Product Pages
Home-page: https://github.com/ktdreyer/txproductpages
Author: Ken Dreyer
Author-email: ktdreyer@ktdreyer.com
License: MIT
Keywords: product pages,twisted
Platform: UNKNOWN
Classifier: Development Status :: 4 - Beta
Classifier: Framework :: Twisted
Classifier: Intended Audience :: Developers
Classifier: License :: OSI Approved :: MIT License
Classifier: Topic :: Software Development
Classifier: Operating System :: OS Independent
Classifier: Programming Language :: Python :: 2.7
Classifier: Programming Language :: Python :: 3.6
